method_override/__init__.py
method_override/middleware.py
method_override/settings.py
method_override/templatetags/__init__.py
method_override/templatetags/method_override.py
django_method_override-1.0.4.dist-info/LICENSE
django_method_override-1.0.4.dist-info/METADATA
django_method_override-1.0.4.dist-info/WHEEL
django_method_override-1.0.4.dist-info/top_level.txt
django_method_override-1.0.4.dist-info/RECORD
